mmmlabs/__init__.py
mmmlabs/cloud_factory.py
mmmlabs/interfaces.py
mmmlabs/providers/__init__.py
mmmlabs/providers/gcp_provider.py
mmmlabs_common-1.1.0.dist-info/METADATA
mmmlabs_common-1.1.0.dist-info/WHEEL
mmmlabs_common-1.1.0.dist-info/entry_points.txt
mmmlabs_common-1.1.0.dist-info/top_level.txt
mmmlabs_common-1.1.0.dist-info/RECORD
