Metadata-Version: 2.4
Name: mmmlabs-common
Version: 1.1.0
Summary: Cloud-agnostic utilities for MMMLabs services
Home-page: https://github.com/mmmlabs/mmmlabs-common
Author: MMM Labs
Author-email: MMM Labs <info@mmmlabs.ai>
Maintainer-email: MMM Labs <info@mmmlabs.ai>
License: MIT
Project-URL: Homepage, https://github.com/mmmlabs/mmmlabs-common
Project-URL: Documentation, https://mmmlabs.github.io/mmmlabs-common
Project-URL: Repository, https://github.com/mmmlabs/mmmlabs-common
Project-URL: Issues, https://github.com/mmmlabs/mmmlabs-common/issues
Project-URL: Changelog, https://github.com/mmmlabs/mmmlabs-common/blob/main/CHANGELOG.md
Keywords: cloud,gcp,azure,aws,utilities,multi-cloud
Classifier: Development Status :: 4 - Beta
Classifier: Intended Audience :: Developers
Classifier: License :: OSI Approved :: MIT License
Classifier: Operating System :: OS Independent
Classifier: Programming Language :: Python :: 3
Classifier: Programming Language :: Python :: 3.11
Classifier: Programming Language :: Python :: 3.12
Classifier: Topic :: Software Development :: Libraries :: Python Modules
Requires-Python: >=3.11
Requires-Dist: pandas>=2.0.0
Requires-Dist: numpy>=1.24.0
Requires-Dist: requests>=2.28.0
Requires-Dist: pydantic>=1.10.0
Requires-Dist: python-dotenv>=1.0.0
Provides-Extra: gcp
Requires-Dist: google-cloud-storage>=2.16.0; extra == "gcp"
Requires-Dist: google-cloud-firestore>=2.16.0; extra == "gcp"
Requires-Dist: google-cloud-pubsub>=2.21.0; extra == "gcp"
Requires-Dist: google-api-python-client>=2.140.0; extra == "gcp"
Provides-Extra: azure
Requires-Dist: azure-storage-blob>=12.17.0; extra == "azure"
Requires-Dist: azure-servicebus>=7.11.0; extra == "azure"
Requires-Dist: azure-cosmos>=4.5.0; extra == "azure"
Requires-Dist: azure-identity>=1.13.0; extra == "azure"
Provides-Extra: aws
Requires-Dist: boto3>=1.28.0; extra == "aws"
Requires-Dist: botocore>=1.31.0; extra == "aws"
Provides-Extra: dev
Requires-Dist: pytest>=7.0.0; extra == "dev"
Requires-Dist: pytest-asyncio>=0.21.0; extra == "dev"
Requires-Dist: pytest-cov>=4.0.0; extra == "dev"
Requires-Dist: black>=23.0.0; extra == "dev"
Requires-Dist: isort>=5.12.0; extra == "dev"
Requires-Dist: flake8>=6.0.0; extra == "dev"
Requires-Dist: mypy>=1.0.0; extra == "dev"
Requires-Dist: bandit[toml]>=1.7.0; extra == "dev"
Requires-Dist: safety>=2.0.0; extra == "dev"
Provides-Extra: all
Requires-Dist: mmmlabs-common[aws,azure,gcp]; extra == "all"
Dynamic: author
Dynamic: home-page
Dynamic: requires-python
